README.rst
setup.cfg
setup.py
pipetree/__init__.py
pipetree.egg-info/PKG-INFO
pipetree.egg-info/SOURCES.txt
pipetree.egg-info/dependency_links.txt
pipetree.egg-info/entry_points.txt
pipetree.egg-info/not-zip-safe
pipetree.egg-info/requires.txt
pipetree.egg-info/top_level.txt
pipetree/cli/__init__.py
pipetree/storage/__init__.py
pipetree/storage/local.py
tests/__init__.py
tests/local_test.py