Metadata-Version: 1.1
Name: pipetree
Version: 0.1.0
Summary: A minimalist data pipeline library and CLI built on top of Spark.
Home-page: https://github.com/mmcdermo/pipetree
Author: Morgan McDermott & John Carlyle
Author-email: pipetree@citrusmode.com
License: MIT
Keywords: pipetree
Platform: UNKNOWN
Classifier: Development Status :: 2 - Pre-Alpha
Classifier: Intended Audience :: Developers
Classifier: Natural Language :: English
Classifier: License :: OSI Approved :: MIT License
Classifier: Programming Language :: Python :: 3
Classifier: Programming Language :: Python :: 3.3
Classifier: Programming Language :: Python :: 3.4
Classifier: Programming Language :: Python :: 3.5
